covidtracking/__init__.py
covidtracking-0.1.dist-info/METADATA
covidtracking-0.1.dist-info/WHEEL
covidtracking-0.1.dist-info/top_level.txt
covidtracking-0.1.dist-info/RECORD
