Metadata-Version: 2.1
Name: covidtracking
Version: 0.1
Summary: Simple API to get data from https://covidtracking.com
Home-page: https://gitlab.com/blfordham/covid-tracking
Author: Bryan L. Fordham
Author-email: bryan@nativesavannah.com
License: UNKNOWN
Platform: UNKNOWN
Classifier: Programming Language :: Python :: 3
Classifier: License :: OSI Approved :: MIT License
Classifier: Operating System :: OS Independent
